pyxbos_dbcli/__init__.py
pyxbos_dbcli-0.1.2.dist-info/WHEEL
pyxbos_dbcli-0.1.2.dist-info/METADATA
pyxbos_dbcli-0.1.2.dist-info/RECORD
